CHANGELOG.md
LICENSE
README.md
fastapi_limiter/__init__.py
fastapi_limiter/depends.py
fastapi_limiter-0.1.3.dist-info/LICENSE
fastapi_limiter-0.1.3.dist-info/WHEEL
fastapi_limiter-0.1.3.dist-info/METADATA
fastapi_limiter-0.1.3.dist-info/RECORD
